README.md
license.txt
setup.py
helpers_base_p1/__init__.py
helpers_base_p1/helpers.py
helpers_base_p1.egg-info/PKG-INFO
helpers_base_p1.egg-info/SOURCES.txt
helpers_base_p1.egg-info/dependency_links.txt
helpers_base_p1.egg-info/top_level.txt