Metadata-Version: 2.1
Name: helpers-base-p1
Version: 0.1.5
Summary: A package containing some helper methods
Author: SomeGuy
License: UNKNOWN
Platform: UNKNOWN
License-File: license.txt
